alibabacloud_agentidentity20250901/__init__.py
alibabacloud_agentidentity20250901/client.py
alibabacloud_agentidentity20250901/models/__init__.py
alibabacloud_agentidentity20250901/models/_authorization_request.py
alibabacloud_agentidentity20250901/models/_authorization_server_metadata.py
alibabacloud_agentidentity20250901/models/_create_apikey_credential_provider_request.py
alibabacloud_agentidentity20250901/models/_create_apikey_credential_provider_response.py
alibabacloud_agentidentity20250901/models/_create_apikey_credential_provider_response_body.py
alibabacloud_agentidentity20250901/models/_create_identity_provider_request.py
alibabacloud_agentidentity20250901/models/_create_identity_provider_response.py
alibabacloud_agentidentity20250901/models/_create_identity_provider_response_body.py
alibabacloud_agentidentity20250901/models/_create_identity_provider_shrink_request.py
alibabacloud_agentidentity20250901/models/_create_oauth2_credential_provider_request.py
alibabacloud_agentidentity20250901/models/_create_oauth2_credential_provider_response.py
alibabacloud_agentidentity20250901/models/_create_oauth2_credential_provider_response_body.py
alibabacloud_agentidentity20250901/models/_create_oauth2_credential_provider_shrink_request.py
alibabacloud_agentidentity20250901/models/_create_workload_identity_request.py
alibabacloud_agentidentity20250901/models/_create_workload_identity_response.py
alibabacloud_agentidentity20250901/models/_create_workload_identity_response_body.py
alibabacloud_agentidentity20250901/models/_create_workload_identity_shrink_request.py
alibabacloud_agentidentity20250901/models/_custom_oauth2_provider_config.py
alibabacloud_agentidentity20250901/models/_delete_apikey_credential_provider_request.py
alibabacloud_agentidentity20250901/models/_delete_apikey_credential_provider_response.py
alibabacloud_agentidentity20250901/models/_delete_apikey_credential_provider_response_body.py
alibabacloud_agentidentity20250901-1.0.0.dist-info/LICENSE
alibabacloud_agentidentity20250901-1.0.0.dist-info/METADATA
alibabacloud_agentidentity20250901-1.0.0.dist-info/WHEEL
alibabacloud_agentidentity20250901-1.0.0.dist-info/top_level.txt
alibabacloud_agentidentity20250901-1.0.0.dist-info/RECORD
